deepai_nlp/__init__.py
deepai_nlp/demo.py
deepai_nlp/utils.py
deepai_nlp/data/sentiment/samples/negative.txt
deepai_nlp/data/sentiment/samples/positive.txt
deepai_nlp/models/pretrained_tokenizer.crfsuite
deepai_nlp/models/pretrained_word2vec.bin
deepai_nlp/text_classification/__init__.py
deepai_nlp/text_classification/short_text_classifiers.py
deepai_nlp/tokenization/__init__.py
deepai_nlp/tokenization/base_tokenizer.py
deepai_nlp/tokenization/bi_grams.txt
deepai_nlp/tokenization/crf_config.txt
deepai_nlp/tokenization/crf_features.txt
deepai_nlp/tokenization/crf_tokenizer.py
deepai_nlp/tokenization/dict_models.py
deepai_nlp/tokenization/tri_grams.txt
deepai_nlp/tokenization/utils.py
deepai_nlp/wikicrawler/__init__.py
deepai_nlp/wikicrawler/wiki_bs4.py
deepai_nlp/word_embedding/__init__.py
deepai_nlp/word_embedding/utils.py
deepai_nlp/word_embedding/word2vec_gensim.py
deepai_nlp-1.0.0.dist-info/METADATA
deepai_nlp-1.0.0.dist-info/WHEEL
deepai_nlp-1.0.0.dist-info/top_level.txt
deepai_nlp-1.0.0.dist-info/RECORD
