Metadata-Version: 2.1
Name: deepai-nlp
Version: 1.0.0
Summary: Project for Vietnamese nlp
Home-page: https://github.com/pypa/sampleproject
Author: DeepAI-Solutions
Author-email: pencil.forever@gmail.com
License: UNKNOWN
Platform: UNKNOWN
Classifier: Programming Language :: Python :: 3
Classifier: License :: OSI Approved :: MIT License
Classifier: Operating System :: OS Independent
Requires-Dist: python-crfsuite (>=0.9.5)
Requires-Dist: sklearn-crfsuite (>=0.3.6)
Requires-Dist: joblib (>=0.12.5)
Requires-Dist: gensim (>=3.5.0)
Requires-Dist: tensorflow (>=1.8.0)
Requires-Dist: keras (>=2.2.0)
